Metadata-Version: 1.0
Name: bin-gauss-distributions
Version: 0.1
Summary: Gaussian distributions and Binomial distribution
Home-page: UNKNOWN
Author: Sajal Jain
Author-email: sajalj4598@gmail.com
License: UNKNOWN
Platform: UNKNOWN
